vrt_lss_registry/__init__.py
vrt_lss_registry/api_client.py
vrt_lss_registry/api_response.py
vrt_lss_registry/configuration.py
vrt_lss_registry/exceptions.py
vrt_lss_registry/py.typed
vrt_lss_registry/rest.py
vrt_lss_registry/api/__init__.py
vrt_lss_registry/api/backups_api.py
vrt_lss_registry/api/configurations_api.py
vrt_lss_registry/api/explorer_api.py
vrt_lss_registry/api/system_api.py
vrt_lss_registry/models/__init__.py
vrt_lss_registry/models/attribute.py
vrt_lss_registry/models/check_result.py
vrt_lss_registry/models/configuration.py
vrt_lss_registry/models/file_name_path.py
vrt_lss_registry/models/file_specification.py
vrt_lss_registry/models/filesystem.py
vrt_lss_registry/models/filesystem_column_type.py
vrt_lss_registry/models/filesystem_counters.py
vrt_lss_registry/models/filesystem_path.py
vrt_lss_registry/models/folder.py
vrt_lss_registry/models/folder_counters.py
vrt_lss_registry/models/folder_specification.py
vrt_lss_registry/models/folder_type.py
vrt_lss_registry/models/general400.py
vrt_lss_registry/models/general402.py
vrt_lss_registry/models/general403.py
vrt_lss_registry/models/general404.py
vrt_lss_registry/models/general404_detail.py
vrt_lss_registry/models/general429.py
vrt_lss_registry/models/general500.py
vrt_lss_registry/models/schema_error.py
vrt_lss_registry/models/service.py
vrt_lss_registry/models/table_configuration.py
vrt_lss_registry/models/table_configuration_column_type.py
vrt_lss_registry/models/table_configuration_list.py
vrt_lss_registry/models/table_list_counters.py
vrt_lss_registry/models/table_list_counters_detail.py
vrt_lss_registry/models/tracedata.py
vrt_lss_registry/models/version_result.py
vrt_lss_registry-7.29.3120.dist-info/METADATA
vrt_lss_registry-7.29.3120.dist-info/WHEEL
vrt_lss_registry-7.29.3120.dist-info/top_level.txt
vrt_lss_registry-7.29.3120.dist-info/RECORD
